pdf2ppt/__init__.py
pdfslides2ppt-1.2.0.dist-info/METADATA
pdfslides2ppt-1.2.0.dist-info/WHEEL
pdfslides2ppt-1.2.0.dist-info/entry_points.txt
pdfslides2ppt-1.2.0.dist-info/top_level.txt
pdfslides2ppt-1.2.0.dist-info/RECORD
