Metadata-Version: 2.4
Name: pdfslides2ppt
Version: 1.2.0
Summary: Convert PDF Slides to PowerPoint Presentations with Vector Graphics
Author-email: Teddy van Jerry <me@wqzhao.org>
Project-URL: Homepage, https://github.com/neosun100/pdf2ppt
Project-URL: Repository, https://github.com/neosun100/pdf2ppt
Project-URL: Issues, https://github.com/neosun100/pdf2ppt/issues
Project-URL: Documentation, https://github.com/neosun100/pdf2ppt#readme
Keywords: pdf,ppt,powerpoint,converter,beamer,typst,touying,slides,vector
Classifier: Development Status :: 4 - Beta
Classifier: Intended Audience :: Developers
Classifier: Intended Audience :: Science/Research
Classifier: License :: OSI Approved :: MIT License
Classifier: Programming Language :: Python :: 3
Classifier: Programming Language :: Python :: 3.9
Classifier: Programming Language :: Python :: 3.10
Classifier: Programming Language :: Python :: 3.11
Classifier: Programming Language :: Python :: 3.12
Classifier: Topic :: Office/Business
Classifier: Topic :: Utilities
Requires-Python: >=3.9
Requires-Dist: python-pptx
Requires-Dist: pypdf
Requires-Dist: rich
Provides-Extra: server
Requires-Dist: fastapi>=0.104.0; extra == "server"
Requires-Dist: uvicorn[standard]>=0.24.0; extra == "server"
Requires-Dist: python-multipart>=0.0.6; extra == "server"
Requires-Dist: jinja2>=3.1.2; extra == "server"
Provides-Extra: mcp
Requires-Dist: fastmcp>=0.1.0; extra == "mcp"
